locust_fixed_interval/__init__.py
locust_fixed_interval-0.1.dist-info/LICENSE
locust_fixed_interval-0.1.dist-info/METADATA
locust_fixed_interval-0.1.dist-info/WHEEL
locust_fixed_interval-0.1.dist-info/top_level.txt
locust_fixed_interval-0.1.dist-info/RECORD
