Metadata-Version: 2.1
Name: locust-fixed-interval
Version: 0.1
Summary: Fixed interval taskset utility package for Locust
Home-page: https://github.com/algattik/locust_fixed_interval
Author: Alexandre Gattiker
Author-email: algattik@microsoft.com
License: UNKNOWN
Platform: UNKNOWN
Classifier: Programming Language :: Python :: 3
Classifier: License :: OSI Approved :: MIT License
Classifier: Operating System :: OS Independent
Requires-Dist: locust
